pelican/plugins/youtube_thumbnails/__init__.py
pelican/plugins/youtube_thumbnails/logo.png
pelican/plugins/youtube_thumbnails/youtube_thumbnails.py
pelican_youtube_thumbnails-0.3.3.dist-info/COPYING
pelican_youtube_thumbnails-0.3.3.dist-info/METADATA
pelican_youtube_thumbnails-0.3.3.dist-info/WHEEL
pelican_youtube_thumbnails-0.3.3.dist-info/top_level.txt
pelican_youtube_thumbnails-0.3.3.dist-info/RECORD
